ancientgram/ancientgram.py
ancientgram-1.0.0.dist-info/METADATA
ancientgram-1.0.0.dist-info/WHEEL
ancientgram-1.0.0.dist-info/top_level.txt
ancientgram-1.0.0.dist-info/RECORD
